docslicer/__init__.py
docslicer/client.py
docslicer-0.1.1.dist-info/METADATA
docslicer-0.1.1.dist-info/WHEEL
docslicer-0.1.1.dist-info/RECORD
