Metadata-Version: 2.4
Name: docslicer
Version: 0.1.1
Summary: SDK for the DocSlicer document processing API - transform HTML documents into structured chunks for RAG applications
Project-URL: Homepage, https://www.docslicer.ai
Project-URL: Documentation, https://www.docslicer.ai/docs
Project-URL: Repository, https://github.com/MarketFramer/docslicer
License: MIT
Keywords: chunking,docslicer,document-processing,html,llm,rag,sec-filings
Classifier: Development Status :: 4 - Beta
Classifier: Intended Audience :: Developers
Classifier: License :: OSI Approved :: MIT License
Classifier: Programming Language :: Python :: 3
Classifier: Programming Language :: Python :: 3.8
Classifier: Programming Language :: Python :: 3.9
Classifier: Programming Language :: Python :: 3.10
Classifier: Programming Language :: Python :: 3.11
Classifier: Programming Language :: Python :: 3.12
Requires-Python: >=3.8
Requires-Dist: httpx>=0.24.0
Provides-Extra: dev
Requires-Dist: pytest-asyncio>=0.21; extra == 'dev'
Requires-Dist: pytest>=7.0; extra == 'dev'
